[
  {
    "page": "/course/00-introduction/01-welcome",
    "illustrations": {
      "found": false,
      "count": 0,
      "issues": []
    },
    "codeBlocks": {
      "count": 0,
      "issues": []
    },
    "layoutIssues": []
  },
  {
    "page": "/course/00-introduction/02-what-is-design-engineering",
    "illustrations": {
      "found": true,
      "count": 1,
      "issues": []
    },
    "codeBlocks": {
      "count": 1,
      "issues": []
    },
    "layoutIssues": []
  },
  {
    "page": "/course/00-introduction/03-choosing-your-path",
    "illustrations": {
      "found": false,
      "count": 0,
      "issues": []
    },
    "codeBlocks": {
      "count": 0,
      "issues": []
    },
    "layoutIssues": []
  },
  {
    "page": "/course/00-introduction/04-how-this-course-works",
    "illustrations": {
      "found": false,
      "count": 0,
      "issues": []
    },
    "codeBlocks": {
      "count": 1,
      "issues": []
    },
    "layoutIssues": []
  },
  {
    "page": "/course/_meta/COURSE-PLAN",
    "illustrations": {
      "found": false,
      "count": 0,
      "issues": []
    },
    "codeBlocks": {
      "count": 13,
      "issues": [
        "Code block 5: Horizontal overflow detected",
        "Code block 7: Horizontal overflow detected",
        "Code block 9: Horizontal overflow detected",
        "Code block 11: Horizontal overflow detected"
      ]
    },
    "layoutIssues": []
  },
  {
    "page": "/course/convergence/android/01-android-motion-and-animation/01-compose-animation",
    "illustrations": {
      "found": false,
      "count": 0,
      "issues": []
    },
    "codeBlocks": {
      "count": 18,
      "issues": [
        "Code block 2: Horizontal overflow detected",
        "Code block 4: Horizontal overflow detected"
      ]
    },
    "layoutIssues": []
  },
  {
    "page": "/course/convergence/android/01-android-motion-and-animation/02-custom-transitions",
    "illustrations": {
      "found": false,
      "count": 0,
      "issues": []
    },
    "codeBlocks": {
      "count": 12,
      "issues": [
        "Code block 2: Horizontal overflow detected"
      ]
    },
    "layoutIssues": []
  },
  {
    "page": "/course/convergence/android/02-prototyping-with-compose/01-prototyping-with-compose",
    "illustrations": {
      "found": false,
      "count": 0,
      "issues": []
    },
    "codeBlocks": {
      "count": 12,
      "issues": []
    },
    "layoutIssues": []
  },
  {
    "page": "/course/convergence/android/03-accessibility-and-polish/01-android-accessibility",
    "illustrations": {
      "found": false,
      "count": 0,
      "issues": []
    },
    "codeBlocks": {
      "count": 12,
      "issues": [
        "Code block 6: Horizontal overflow detected"
      ]
    },
    "layoutIssues": []
  },
  {
    "page": "/course/convergence/android/03-accessibility-and-polish/02-polish-and-details",
    "illustrations": {
      "found": false,
      "count": 0,
      "issues": []
    },
    "codeBlocks": {
      "count": 14,
      "issues": [
        "Code block 2: Horizontal overflow detected",
        "Code block 4: Horizontal overflow detected",
        "Code block 6: Horizontal overflow detected",
        "Code block 10: Horizontal overflow detected"
      ]
    },
    "layoutIssues": []
  },
  {
    "page": "/course/convergence/index",
    "illustrations": {
      "found": false,
      "count": 0,
      "issues": []
    },
    "codeBlocks": {
      "count": 0,
      "issues": []
    },
    "layoutIssues": []
  },
  {
    "page": "/course/convergence/ios/01-ios-motion-and-animation/01-swiftui-animation",
    "illustrations": {
      "found": false,
      "count": 0,
      "issues": []
    },
    "codeBlocks": {
      "count": 12,
      "issues": [
        "Code block 10: Horizontal overflow detected"
      ]
    },
    "layoutIssues": []
  },
  {
    "page": "/course/convergence/ios/01-ios-motion-and-animation/02-custom-transitions",
    "illustrations": {
      "found": false,
      "count": 0,
      "issues": []
    },
    "codeBlocks": {
      "count": 12,
      "issues": [
        "Code block 4: Horizontal overflow detected",
        "Code block 10: Horizontal overflow detected"
      ]
    },
    "layoutIssues": []
  },
  {
    "page": "/course/convergence/ios/02-prototyping-with-swiftui/01-prototyping-with-swiftui",
    "illustrations": {
      "found": false,
      "count": 0,
      "issues": []
    },
    "codeBlocks": {
      "count": 10,
      "issues": []
    },
    "layoutIssues": []
  },
  {
    "page": "/course/convergence/ios/03-accessibility-and-polish/01-ios-accessibility",
    "illustrations": {
      "found": false,
      "count": 0,
      "issues": []
    },
    "codeBlocks": {
      "count": 14,
      "issues": []
    },
    "layoutIssues": []
  },
  {
    "page": "/course/convergence/ios/03-accessibility-and-polish/02-polish-and-details",
    "illustrations": {
      "found": false,
      "count": 0,
      "issues": []
    },
    "codeBlocks": {
      "count": 10,
      "issues": [
        "Code block 6: Horizontal overflow detected",
        "Code block 8: Horizontal overflow detected",
        "Code block 10: Horizontal overflow detected"
      ]
    },
    "layoutIssues": []
  },
  {
    "page": "/course/convergence/web/01-motion-and-interaction/01-why-motion-matters",
    "illustrations": {
      "found": false,
      "count": 0,
      "issues": []
    },
    "codeBlocks": {
      "count": 0,
      "issues": []
    },
    "layoutIssues": []
  },
  {
    "page": "/course/convergence/web/01-motion-and-interaction/02-principles-of-ui-animation",
    "illustrations": {
      "found": false,
      "count": 0,
      "issues": []
    },
    "codeBlocks": {
      "count": 12,
      "issues": []
    },
    "layoutIssues": []
  },
  {
    "page": "/course/convergence/web/01-motion-and-interaction/03-micro-interactions",
    "illustrations": {
      "found": false,
      "count": 0,
      "issues": []
    },
    "codeBlocks": {
      "count": 20,
      "issues": []
    },
    "layoutIssues": []
  },
  {
    "page": "/course/convergence/web/01-motion-and-interaction/04-page-transitions",
    "illustrations": {
      "found": false,
      "count": 0,
      "issues": []
    },
    "codeBlocks": {
      "count": 16,
      "issues": []
    },
    "layoutIssues": []
  },
  {
    "page": "/course/convergence/web/01-motion-and-interaction/05-scroll-based-animation",
    "illustrations": {
      "found": false,
      "count": 0,
      "issues": []
    },
    "codeBlocks": {
      "count": 16,
      "issues": [
        "Code block 14: Horizontal overflow detected"
      ]
    },
    "layoutIssues": []
  },
  {
    "page": "/course/convergence/web/01-motion-and-interaction/06-implementing-motion",
    "illustrations": {
      "found": false,
      "count": 0,
      "issues": []
    },
    "codeBlocks": {
      "count": 20,
      "issues": [
        "Code block 2: Horizontal overflow detected",
        "Code block 4: Horizontal overflow detected",
        "Code block 8: Horizontal overflow detected"
      ]
    },
    "layoutIssues": []
  },
  {
    "page": "/course/convergence/web/02-prototyping/01-prototyping-mindset",
    "illustrations": {
      "found": false,
      "count": 0,
      "issues": []
    },
    "codeBlocks": {
      "count": 0,
      "issues": []
    },
    "layoutIssues": []
  },
  {
    "page": "/course/convergence/web/02-prototyping/02-from-design-to-prototype",
    "illustrations": {
      "found": false,
      "count": 0,
      "issues": []
    },
    "codeBlocks": {
      "count": 6,
      "issues": []
    },
    "layoutIssues": []
  },
  {
    "page": "/course/convergence/web/02-prototyping/03-prototype-to-production",
    "illustrations": {
      "found": false,
      "count": 0,
      "issues": []
    },
    "codeBlocks": {
      "count": 8,
      "issues": []
    },
    "layoutIssues": []
  },
  {
    "page": "/course/convergence/web/02-prototyping/04-selling-with-prototypes",
    "illustrations": {
      "found": false,
      "count": 0,
      "issues": []
    },
    "codeBlocks": {
      "count": 0,
      "issues": []
    },
    "layoutIssues": []
  },
  {
    "page": "/course/convergence/web/02-prototyping/05-tools-and-techniques",
    "illustrations": {
      "found": false,
      "count": 0,
      "issues": []
    },
    "codeBlocks": {
      "count": 6,
      "issues": [
        "Code block 4: Horizontal overflow detected"
      ]
    },
    "layoutIssues": []
  },
  {
    "page": "/course/convergence/web/03-accessibility/01-accessibility-foundations",
    "illustrations": {
      "found": false,
      "count": 0,
      "issues": []
    },
    "codeBlocks": {
      "count": 0,
      "issues": []
    },
    "layoutIssues": []
  },
  {
    "page": "/course/convergence/web/03-accessibility/02-semantic-html-for-a11y",
    "illustrations": {
      "found": false,
      "count": 0,
      "issues": []
    },
    "codeBlocks": {
      "count": 14,
      "issues": [
        "Code block 10: Horizontal overflow detected"
      ]
    },
    "layoutIssues": []
  },
  {
    "page": "/course/convergence/web/03-accessibility/03-keyboard-navigation",
    "illustrations": {
      "found": false,
      "count": 0,
      "issues": []
    },
    "codeBlocks": {
      "count": 12,
      "issues": [
        "Code block 8: Horizontal overflow detected",
        "Code block 10: Horizontal overflow detected"
      ]
    },
    "layoutIssues": []
  },
  {
    "page": "/course/convergence/web/03-accessibility/04-screen-reader-experience",
    "illustrations": {
      "found": false,
      "count": 0,
      "issues": []
    },
    "codeBlocks": {
      "count": 14,
      "issues": []
    },
    "layoutIssues": []
  },
  {
    "page": "/course/convergence/web/03-accessibility/05-color-and-contrast",
    "illustrations": {
      "found": false,
      "count": 0,
      "issues": []
    },
    "codeBlocks": {
      "count": 8,
      "issues": [
        "Code block 6: Horizontal overflow detected"
      ]
    },
    "layoutIssues": []
  },
  {
    "page": "/course/convergence/web/03-accessibility/06-motion-and-accessibility",
    "illustrations": {
      "found": false,
      "count": 0,
      "issues": []
    },
    "codeBlocks": {
      "count": 14,
      "issues": [
        "Code block 8: Horizontal overflow detected",
        "Code block 14: Horizontal overflow detected"
      ]
    },
    "layoutIssues": []
  },
  {
    "page": "/course/convergence/web/04-performance-and-polish/01-perceived-performance",
    "illustrations": {
      "found": false,
      "count": 0,
      "issues": []
    },
    "codeBlocks": {
      "count": 14,
      "issues": []
    },
    "layoutIssues": []
  },
  {
    "page": "/course/convergence/web/04-performance-and-polish/02-image-optimization",
    "illustrations": {
      "found": false,
      "count": 0,
      "issues": []
    },
    "codeBlocks": {
      "count": 14,
      "issues": [
        "Code block 12: Horizontal overflow detected"
      ]
    },
    "layoutIssues": []
  },
  {
    "page": "/course/convergence/web/04-performance-and-polish/03-css-performance",
    "illustrations": {
      "found": false,
      "count": 0,
      "issues": []
    },
    "codeBlocks": {
      "count": 14,
      "issues": [
        "Code block 12: Horizontal overflow detected"
      ]
    },
    "layoutIssues": []
  },
  {
    "page": "/course/convergence/web/04-performance-and-polish/04-javascript-performance",
    "illustrations": {
      "found": false,
      "count": 0,
      "issues": []
    },
    "codeBlocks": {
      "count": 14,
      "issues": []
    },
    "layoutIssues": []
  },
  {
    "page": "/course/convergence/web/04-performance-and-polish/05-the-details-matter",
    "illustrations": {
      "found": false,
      "count": 0,
      "issues": []
    },
    "codeBlocks": {
      "count": 8,
      "issues": [
        "Code block 4: Horizontal overflow detected"
      ]
    },
    "layoutIssues": []
  },
  {
    "page": "/course/convergence/web/05-workflow-and-portfolio/01-the-de-workflow",
    "illustrations": {
      "found": false,
      "count": 0,
      "issues": []
    },
    "codeBlocks": {
      "count": 1,
      "issues": [
        "Code block 1: Height too small (28px)"
      ]
    },
    "layoutIssues": []
  },
  {
    "page": "/course/convergence/web/05-workflow-and-portfolio/02-bridging-design-and-eng",
    "illustrations": {
      "found": false,
      "count": 0,
      "issues": []
    },
    "codeBlocks": {
      "count": 0,
      "issues": []
    },
    "layoutIssues": []
  },
  {
    "page": "/course/convergence/web/05-workflow-and-portfolio/03-side-projects",
    "illustrations": {
      "found": false,
      "count": 0,
      "issues": []
    },
    "codeBlocks": {
      "count": 0,
      "issues": []
    },
    "layoutIssues": []
  },
  {
    "page": "/course/convergence/web/05-workflow-and-portfolio/04-building-your-portfolio",
    "illustrations": {
      "found": false,
      "count": 0,
      "issues": []
    },
    "codeBlocks": {
      "count": 0,
      "issues": []
    },
    "layoutIssues": []
  },
  {
    "page": "/course/convergence/web/05-workflow-and-portfolio/05-finding-de-roles",
    "illustrations": {
      "found": false,
      "count": 0,
      "issues": []
    },
    "codeBlocks": {
      "count": 0,
      "issues": []
    },
    "layoutIssues": []
  },
  {
    "page": "/course/design-track/android/01-material-design/01-material-design-philosophy",
    "illustrations": {
      "found": false,
      "count": 0,
      "issues": []
    },
    "codeBlocks": {
      "count": 0,
      "issues": []
    },
    "layoutIssues": []
  },
  {
    "page": "/course/design-track/android/01-material-design/02-material-foundations",
    "illustrations": {
      "found": false,
      "count": 0,
      "issues": []
    },
    "codeBlocks": {
      "count": 0,
      "issues": []
    },
    "layoutIssues": []
  },
  {
    "page": "/course/design-track/android/01-material-design/03-elevation-and-surfaces",
    "illustrations": {
      "found": false,
      "count": 0,
      "issues": []
    },
    "codeBlocks": {
      "count": 1,
      "issues": []
    },
    "layoutIssues": []
  },
  {
    "page": "/course/design-track/android/01-material-design/04-theming-and-customization",
    "illustrations": {
      "found": false,
      "count": 0,
      "issues": []
    },
    "codeBlocks": {
      "count": 1,
      "issues": []
    },
    "layoutIssues": []
  },
  {
    "page": "/course/design-track/android/02-android-design-patterns/01-android-navigation",
    "illustrations": {
      "found": false,
      "count": 0,
      "issues": []
    },
    "codeBlocks": {
      "count": 1,
      "issues": []
    },
    "layoutIssues": []
  },
  {
    "page": "/course/design-track/android/02-android-design-patterns/02-android-components",
    "illustrations": {
      "found": false,
      "count": 0,
      "issues": []
    },
    "codeBlocks": {
      "count": 0,
      "issues": []
    },
    "layoutIssues": []
  },
  {
    "page": "/course/design-track/android/02-android-design-patterns/03-android-layout-system",
    "illustrations": {
      "found": false,
      "count": 0,
      "issues": []
    },
    "codeBlocks": {
      "count": 0,
      "issues": []
    },
    "layoutIssues": []
  },
  {
    "page": "/course/design-track/android/02-android-design-patterns/04-notifications-and-widgets",
    "illustrations": {
      "found": false,
      "count": 0,
      "issues": []
    },
    "codeBlocks": {
      "count": 0,
      "issues": []
    },
    "layoutIssues": []
  },
  {
    "page": "/course/design-track/android/03-designing-for-android/01-designing-android-apps-in-figma",
    "illustrations": {
      "found": false,
      "count": 0,
      "issues": []
    },
    "codeBlocks": {
      "count": 1,
      "issues": []
    },
    "layoutIssues": []
  },
  {
    "page": "/course/design-track/android/03-designing-for-android/02-adaptive-and-responsive",
    "illustrations": {
      "found": false,
      "count": 0,
      "issues": []
    },
    "codeBlocks": {
      "count": 0,
      "issues": []
    },
    "layoutIssues": []
  },
  {
    "page": "/course/design-track/android/03-designing-for-android/03-android-motion-principles",
    "illustrations": {
      "found": false,
      "count": 0,
      "issues": []
    },
    "codeBlocks": {
      "count": 1,
      "issues": []
    },
    "layoutIssues": []
  },
  {
    "page": "/course/design-track/android/03-designing-for-android/04-from-design-to-compose",
    "illustrations": {
      "found": false,
      "count": 0,
      "issues": []
    },
    "codeBlocks": {
      "count": 7,
      "issues": [
        "Code block 5: Horizontal overflow detected"
      ]
    },
    "layoutIssues": []
  },
  {
    "page": "/course/design-track/index",
    "illustrations": {
      "found": false,
      "count": 0,
      "issues": []
    },
    "codeBlocks": {
      "count": 0,
      "issues": []
    },
    "layoutIssues": []
  },
  {
    "page": "/course/design-track/ios/01-hig-fundamentals/01-ios-design-philosophy",
    "illustrations": {
      "found": false,
      "count": 0,
      "issues": []
    },
    "codeBlocks": {
      "count": 0,
      "issues": []
    },
    "layoutIssues": []
  },
  {
    "page": "/course/design-track/ios/01-hig-fundamentals/02-navigation-paradigms",
    "illustrations": {
      "found": false,
      "count": 0,
      "issues": []
    },
    "codeBlocks": {
      "count": 1,
      "issues": []
    },
    "layoutIssues": []
  },
  {
    "page": "/course/design-track/ios/01-hig-fundamentals/03-ios-typography",
    "illustrations": {
      "found": false,
      "count": 0,
      "issues": []
    },
    "codeBlocks": {
      "count": 0,
      "issues": []
    },
    "layoutIssues": []
  },
  {
    "page": "/course/design-track/ios/01-hig-fundamentals/04-ios-color-and-materials",
    "illustrations": {
      "found": false,
      "count": 0,
      "issues": []
    },
    "codeBlocks": {
      "count": 0,
      "issues": []
    },
    "layoutIssues": []
  },
  {
    "page": "/course/design-track/ios/02-ios-design-patterns/01-standard-ui-components",
    "illustrations": {
      "found": false,
      "count": 0,
      "issues": []
    },
    "codeBlocks": {
      "count": 0,
      "issues": []
    },
    "layoutIssues": []
  },
  {
    "page": "/course/design-track/ios/02-ios-design-patterns/02-touch-and-gestures",
    "illustrations": {
      "found": false,
      "count": 0,
      "issues": []
    },
    "codeBlocks": {
      "count": 0,
      "issues": []
    },
    "layoutIssues": []
  },
  {
    "page": "/course/design-track/ios/02-ios-design-patterns/03-safe-areas-and-layout",
    "illustrations": {
      "found": false,
      "count": 0,
      "issues": []
    },
    "codeBlocks": {
      "count": 1,
      "issues": []
    },
    "layoutIssues": []
  },
  {
    "page": "/course/design-track/ios/02-ios-design-patterns/04-widgets-and-extensions",
    "illustrations": {
      "found": false,
      "count": 0,
      "issues": []
    },
    "codeBlocks": {
      "count": 0,
      "issues": []
    },
    "layoutIssues": []
  },
  {
    "page": "/course/design-track/ios/03-designing-for-ios/01-designing-ios-apps-in-figma",
    "illustrations": {
      "found": false,
      "count": 0,
      "issues": []
    },
    "codeBlocks": {
      "count": 1,
      "issues": []
    },
    "layoutIssues": []
  },
  {
    "page": "/course/design-track/ios/03-designing-for-ios/02-adaptive-layouts",
    "illustrations": {
      "found": false,
      "count": 0,
      "issues": []
    },
    "codeBlocks": {
      "count": 0,
      "issues": []
    },
    "layoutIssues": []
  },
  {
    "page": "/course/design-track/ios/03-designing-for-ios/03-ios-animation-principles",
    "illustrations": {
      "found": false,
      "count": 0,
      "issues": []
    },
    "codeBlocks": {
      "count": 1,
      "issues": []
    },
    "layoutIssues": []
  },
  {
    "page": "/course/design-track/ios/03-designing-for-ios/04-from-design-to-swiftui",
    "illustrations": {
      "found": false,
      "count": 0,
      "issues": []
    },
    "codeBlocks": {
      "count": 7,
      "issues": []
    },
    "layoutIssues": []
  },
  {
    "page": "/course/design-track/web/01-foundations/01-what-is-visual-design",
    "illustrations": {
      "found": true,
      "count": 1,
      "issues": []
    },
    "codeBlocks": {
      "count": 0,
      "issues": []
    },
    "layoutIssues": []
  },
  {
    "page": "/course/design-track/web/01-foundations/02-principles-of-design",
    "illustrations": {
      "found": false,
      "count": 0,
      "issues": []
    },
    "codeBlocks": {
      "count": 0,
      "issues": []
    },
    "layoutIssues": []
  },
  {
    "page": "/course/design-track/web/01-foundations/03-gestalt-principles",
    "illustrations": {
      "found": true,
      "count": 1,
      "issues": []
    },
    "codeBlocks": {
      "count": 0,
      "issues": []
    },
    "layoutIssues": []
  },
  {
    "page": "/course/design-track/web/01-foundations/04-designing-with-intention",
    "illustrations": {
      "found": false,
      "count": 0,
      "issues": []
    },
    "codeBlocks": {
      "count": 1,
      "issues": []
    },
    "layoutIssues": []
  },
  {
    "page": "/course/design-track/web/02-visual-design/01-typography-fundamentals",
    "illustrations": {
      "found": true,
      "count": 1,
      "issues": []
    },
    "codeBlocks": {
      "count": 10,
      "issues": [
        "Code block 6: Horizontal overflow detected",
        "Code block 8: Horizontal overflow detected"
      ]
    },
    "layoutIssues": []
  },
  {
    "page": "/course/design-track/web/02-visual-design/02-color-theory-and-application",
    "illustrations": {
      "found": true,
      "count": 1,
      "issues": []
    },
    "codeBlocks": {
      "count": 13,
      "issues": [
        "Code block 9: Horizontal overflow detected"
      ]
    },
    "layoutIssues": []
  },
  {
    "page": "/course/design-track/web/02-visual-design/03-spacing-and-rhythm",
    "illustrations": {
      "found": false,
      "count": 0,
      "issues": []
    },
    "codeBlocks": {
      "count": 17,
      "issues": [
        "Code block 1: Height too small (28px)",
        "Code block 2: Height too small (28px)"
      ]
    },
    "layoutIssues": []
  },
  {
    "page": "/course/design-track/web/02-visual-design/04-layout-and-composition",
    "illustrations": {
      "found": false,
      "count": 0,
      "issues": []
    },
    "codeBlocks": {
      "count": 3,
      "issues": []
    },
    "layoutIssues": []
  },
  {
    "page": "/course/design-track/web/02-visual-design/05-iconography-and-imagery",
    "illustrations": {
      "found": false,
      "count": 0,
      "issues": []
    },
    "codeBlocks": {
      "count": 4,
      "issues": []
    },
    "layoutIssues": []
  },
  {
    "page": "/course/design-track/web/03-design-tools/01-thinking-in-components",
    "illustrations": {
      "found": false,
      "count": 0,
      "issues": []
    },
    "codeBlocks": {
      "count": 1,
      "issues": []
    },
    "layoutIssues": []
  },
  {
    "page": "/course/design-track/web/03-design-tools/02-design-tool-fundamentals",
    "illustrations": {
      "found": false,
      "count": 0,
      "issues": []
    },
    "codeBlocks": {
      "count": 2,
      "issues": []
    },
    "layoutIssues": []
  },
  {
    "page": "/course/design-track/web/03-design-tools/03-auto-layout-and-constraints",
    "illustrations": {
      "found": false,
      "count": 0,
      "issues": []
    },
    "codeBlocks": {
      "count": 9,
      "issues": [
        "Code block 4: Height too small (28px)"
      ]
    },
    "layoutIssues": []
  },
  {
    "page": "/course/design-track/web/03-design-tools/04-prototyping-basics",
    "illustrations": {
      "found": false,
      "count": 0,
      "issues": []
    },
    "codeBlocks": {
      "count": 0,
      "issues": []
    },
    "layoutIssues": []
  },
  {
    "page": "/course/design-track/web/03-design-tools/05-collaboration-and-handoff",
    "illustrations": {
      "found": false,
      "count": 0,
      "issues": []
    },
    "codeBlocks": {
      "count": 5,
      "issues": []
    },
    "layoutIssues": []
  },
  {
    "page": "/course/design-track/web/04-design-systems/01-what-is-a-design-system",
    "illustrations": {
      "found": false,
      "count": 0,
      "issues": []
    },
    "codeBlocks": {
      "count": 0,
      "issues": []
    },
    "layoutIssues": []
  },
  {
    "page": "/course/design-track/web/04-design-systems/02-tokens-and-variables",
    "illustrations": {
      "found": false,
      "count": 0,
      "issues": []
    },
    "codeBlocks": {
      "count": 19,
      "issues": []
    },
    "layoutIssues": []
  },
  {
    "page": "/course/design-track/web/04-design-systems/03-component-architecture",
    "illustrations": {
      "found": false,
      "count": 0,
      "issues": []
    },
    "codeBlocks": {
      "count": 8,
      "issues": [
        "Code block 3: Height too small (28px)"
      ]
    },
    "layoutIssues": []
  },
  {
    "page": "/course/design-track/web/04-design-systems/04-documentation-that-works",
    "illustrations": {
      "found": false,
      "count": 0,
      "issues": []
    },
    "codeBlocks": {
      "count": 5,
      "issues": [
        "Code block 5: Height too small (28px)"
      ]
    },
    "layoutIssues": []
  },
  {
    "page": "/course/design-track/web/04-design-systems/05-maintaining-and-evolving",
    "illustrations": {
      "found": false,
      "count": 0,
      "issues": []
    },
    "codeBlocks": {
      "count": 0,
      "issues": []
    },
    "layoutIssues": []
  },
  {
    "page": "/course/design-track/web/05-ux-principles/01-user-centered-thinking",
    "illustrations": {
      "found": false,
      "count": 0,
      "issues": []
    },
    "codeBlocks": {
      "count": 0,
      "issues": []
    },
    "layoutIssues": []
  },
  {
    "page": "/course/design-track/web/05-ux-principles/02-information-architecture",
    "illustrations": {
      "found": false,
      "count": 0,
      "issues": []
    },
    "codeBlocks": {
      "count": 2,
      "issues": [
        "Code block 1: Height too small (28px)"
      ]
    },
    "layoutIssues": []
  },
  {
    "page": "/course/design-track/web/05-ux-principles/03-interaction-design-basics",
    "illustrations": {
      "found": false,
      "count": 0,
      "issues": []
    },
    "codeBlocks": {
      "count": 0,
      "issues": []
    },
    "layoutIssues": []
  },
  {
    "page": "/course/design-track/web/05-ux-principles/04-usability-heuristics",
    "illustrations": {
      "found": false,
      "count": 0,
      "issues": []
    },
    "codeBlocks": {
      "count": 0,
      "issues": []
    },
    "layoutIssues": []
  },
  {
    "page": "/course/design-track/web/05-ux-principles/05-designing-for-edge-cases",
    "illustrations": {
      "found": false,
      "count": 0,
      "issues": []
    },
    "codeBlocks": {
      "count": 3,
      "issues": []
    },
    "layoutIssues": []
  },
  {
    "page": "/course/engineering-track/android/01-kotlin-basics/01-introduction-to-kotlin",
    "illustrations": {
      "found": false,
      "count": 0,
      "issues": []
    },
    "codeBlocks": {
      "count": 16,
      "issues": []
    },
    "layoutIssues": []
  },
  {
    "page": "/course/engineering-track/android/01-kotlin-basics/02-variables-and-types",
    "illustrations": {
      "found": false,
      "count": 0,
      "issues": []
    },
    "codeBlocks": {
      "count": 24,
      "issues": [
        "Code block 24: Horizontal overflow detected"
      ]
    },
    "layoutIssues": []
  },
  {
    "page": "/course/engineering-track/android/01-kotlin-basics/03-collections",
    "illustrations": {
      "found": false,
      "count": 0,
      "issues": []
    },
    "codeBlocks": {
      "count": 20,
      "issues": []
    },
    "layoutIssues": []
  },
  {
    "page": "/course/engineering-track/android/01-kotlin-basics/04-control-flow",
    "illustrations": {
      "found": false,
      "count": 0,
      "issues": []
    },
    "codeBlocks": {
      "count": 12,
      "issues": []
    },
    "layoutIssues": []
  },
  {
    "page": "/course/engineering-track/android/01-kotlin-basics/05-functions-and-lambdas",
    "illustrations": {
      "found": false,
      "count": 0,
      "issues": []
    },
    "codeBlocks": {
      "count": 22,
      "issues": [
        "Code block 10: Horizontal overflow detected"
      ]
    },
    "layoutIssues": []
  },
  {
    "page": "/course/engineering-track/android/01-kotlin-basics/06-classes-and-data-classes",
    "illustrations": {
      "found": false,
      "count": 0,
      "issues": []
    },
    "codeBlocks": {
      "count": 14,
      "issues": []
    },
    "layoutIssues": []
  },
  {
    "page": "/course/engineering-track/android/02-compose-fundamentals/01-what-is-compose",
    "illustrations": {
      "found": false,
      "count": 0,
      "issues": []
    },
    "codeBlocks": {
      "count": 14,
      "issues": []
    },
    "layoutIssues": []
  },
  {
    "page": "/course/engineering-track/android/02-compose-fundamentals/02-composables-and-modifiers",
    "illustrations": {
      "found": false,
      "count": 0,
      "issues": []
    },
    "codeBlocks": {
      "count": 20,
      "issues": [
        "Code block 12: Horizontal overflow detected"
      ]
    },
    "layoutIssues": []
  },
  {
    "page": "/course/engineering-track/android/02-compose-fundamentals/03-layout-basics",
    "illustrations": {
      "found": false,
      "count": 0,
      "issues": []
    },
    "codeBlocks": {
      "count": 14,
      "issues": [
        "Code block 6: Horizontal overflow detected",
        "Code block 8: Horizontal overflow detected",
        "Code block 14: Horizontal overflow detected"
      ]
    },
    "layoutIssues": []
  },
  {
    "page": "/course/engineering-track/android/02-compose-fundamentals/04-state-management",
    "illustrations": {
      "found": false,
      "count": 0,
      "issues": []
    },
    "codeBlocks": {
      "count": 14,
      "issues": []
    },
    "layoutIssues": []
  },
  {
    "page": "/course/engineering-track/android/02-compose-fundamentals/05-lists-and-navigation",
    "illustrations": {
      "found": false,
      "count": 0,
      "issues": []
    },
    "codeBlocks": {
      "count": 16,
      "issues": [
        "Code block 14: Horizontal overflow detected"
      ]
    },
    "layoutIssues": []
  },
  {
    "page": "/course/engineering-track/android/02-compose-fundamentals/06-theming",
    "illustrations": {
      "found": false,
      "count": 0,
      "issues": []
    },
    "codeBlocks": {
      "count": 14,
      "issues": [
        "Code block 2: Horizontal overflow detected",
        "Code block 12: Horizontal overflow detected"
      ]
    },
    "layoutIssues": []
  },
  {
    "page": "/course/engineering-track/android/03-building-interfaces/01-building-a-button",
    "illustrations": {
      "found": false,
      "count": 0,
      "issues": []
    },
    "codeBlocks": {
      "count": 12,
      "issues": [
        "Code block 4: Horizontal overflow detected",
        "Code block 8: Horizontal overflow detected",
        "Code block 12: Horizontal overflow detected"
      ]
    },
    "layoutIssues": []
  },
  {
    "page": "/course/engineering-track/android/03-building-interfaces/02-building-a-card",
    "illustrations": {
      "found": false,
      "count": 0,
      "issues": []
    },
    "codeBlocks": {
      "count": 10,
      "issues": [
        "Code block 4: Horizontal overflow detected",
        "Code block 6: Horizontal overflow detected",
        "Code block 8: Horizontal overflow detected"
      ]
    },
    "layoutIssues": []
  },
  {
    "page": "/course/engineering-track/android/03-building-interfaces/03-building-a-list-item",
    "illustrations": {
      "found": false,
      "count": 0,
      "issues": []
    },
    "codeBlocks": {
      "count": 8,
      "issues": [
        "Code block 2: Horizontal overflow detected",
        "Code block 6: Horizontal overflow detected",
        "Code block 8: Horizontal overflow detected"
      ]
    },
    "layoutIssues": []
  },
  {
    "page": "/course/engineering-track/android/03-building-interfaces/04-building-a-form",
    "illustrations": {
      "found": false,
      "count": 0,
      "issues": []
    },
    "codeBlocks": {
      "count": 10,
      "issues": [
        "Code block 4: Horizontal overflow detected",
        "Code block 6: Horizontal overflow detected",
        "Code block 8: Horizontal overflow detected",
        "Code block 10: Horizontal overflow detected"
      ]
    },
    "layoutIssues": []
  },
  {
    "page": "/course/engineering-track/android/03-building-interfaces/05-custom-composables",
    "illustrations": {
      "found": false,
      "count": 0,
      "issues": []
    },
    "codeBlocks": {
      "count": 16,
      "issues": [
        "Code block 2: Horizontal overflow detected",
        "Code block 4: Horizontal overflow detected",
        "Code block 6: Horizontal overflow detected",
        "Code block 8: Horizontal overflow detected",
        "Code block 10: Horizontal overflow detected"
      ]
    },
    "layoutIssues": []
  },
  {
    "page": "/course/engineering-track/index",
    "illustrations": {
      "found": false,
      "count": 0,
      "issues": []
    },
    "codeBlocks": {
      "count": 0,
      "issues": []
    },
    "layoutIssues": []
  },
  {
    "page": "/course/engineering-track/ios/01-swift-basics/01-introduction-to-swift",
    "illustrations": {
      "found": false,
      "count": 0,
      "issues": []
    },
    "codeBlocks": {
      "count": 14,
      "issues": []
    },
    "layoutIssues": []
  },
  {
    "page": "/course/engineering-track/ios/01-swift-basics/02-variables-and-types",
    "illustrations": {
      "found": false,
      "count": 0,
      "issues": []
    },
    "codeBlocks": {
      "count": 24,
      "issues": []
    },
    "layoutIssues": []
  },
  {
    "page": "/course/engineering-track/ios/01-swift-basics/03-collections",
    "illustrations": {
      "found": false,
      "count": 0,
      "issues": []
    },
    "codeBlocks": {
      "count": 20,
      "issues": []
    },
    "layoutIssues": []
  },
  {
    "page": "/course/engineering-track/ios/01-swift-basics/04-control-flow",
    "illustrations": {
      "found": false,
      "count": 0,
      "issues": []
    },
    "codeBlocks": {
      "count": 22,
      "issues": []
    },
    "layoutIssues": []
  },
  {
    "page": "/course/engineering-track/ios/01-swift-basics/05-functions-and-closures",
    "illustrations": {
      "found": false,
      "count": 0,
      "issues": []
    },
    "codeBlocks": {
      "count": 24,
      "issues": [
        "Code block 14: Horizontal overflow detected"
      ]
    },
    "layoutIssues": []
  },
  {
    "page": "/course/engineering-track/ios/01-swift-basics/06-structs-and-classes",
    "illustrations": {
      "found": false,
      "count": 0,
      "issues": []
    },
    "codeBlocks": {
      "count": 16,
      "issues": []
    },
    "layoutIssues": []
  },
  {
    "page": "/course/engineering-track/ios/02-swiftui-fundamentals/01-what-is-swiftui",
    "illustrations": {
      "found": false,
      "count": 0,
      "issues": []
    },
    "codeBlocks": {
      "count": 20,
      "issues": []
    },
    "layoutIssues": []
  },
  {
    "page": "/course/engineering-track/ios/02-swiftui-fundamentals/02-views-and-modifiers",
    "illustrations": {
      "found": false,
      "count": 0,
      "issues": []
    },
    "codeBlocks": {
      "count": 18,
      "issues": []
    },
    "layoutIssues": []
  },
  {
    "page": "/course/engineering-track/ios/02-swiftui-fundamentals/03-layout-basics",
    "illustrations": {
      "found": false,
      "count": 0,
      "issues": []
    },
    "codeBlocks": {
      "count": 18,
      "issues": []
    },
    "layoutIssues": []
  },
  {
    "page": "/course/engineering-track/ios/02-swiftui-fundamentals/04-state-management",
    "illustrations": {
      "found": false,
      "count": 0,
      "issues": []
    },
    "codeBlocks": {
      "count": 9,
      "issues": [
        "Code block 7: Horizontal overflow detected"
      ]
    },
    "layoutIssues": []
  },
  {
    "page": "/course/engineering-track/ios/02-swiftui-fundamentals/05-lists-and-navigation",
    "illustrations": {
      "found": false,
      "count": 0,
      "issues": []
    },
    "codeBlocks": {
      "count": 18,
      "issues": []
    },
    "layoutIssues": []
  },
  {
    "page": "/course/engineering-track/ios/02-swiftui-fundamentals/06-styling-and-theming",
    "illustrations": {
      "found": false,
      "count": 0,
      "issues": []
    },
    "codeBlocks": {
      "count": 20,
      "issues": [
        "Code block 2: Horizontal overflow detected"
      ]
    },
    "layoutIssues": []
  },
  {
    "page": "/course/engineering-track/ios/03-building-interfaces/01-building-a-button",
    "illustrations": {
      "found": false,
      "count": 0,
      "issues": []
    },
    "codeBlocks": {
      "count": 12,
      "issues": [
        "Code block 6: Horizontal overflow detected",
        "Code block 10: Horizontal overflow detected",
        "Code block 12: Horizontal overflow detected"
      ]
    },
    "layoutIssues": []
  },
  {
    "page": "/course/engineering-track/ios/03-building-interfaces/02-building-a-card",
    "illustrations": {
      "found": false,
      "count": 0,
      "issues": []
    },
    "codeBlocks": {
      "count": 8,
      "issues": [
        "Code block 2: Horizontal overflow detected",
        "Code block 6: Horizontal overflow detected"
      ]
    },
    "layoutIssues": []
  },
  {
    "page": "/course/engineering-track/ios/03-building-interfaces/03-building-a-list-row",
    "illustrations": {
      "found": false,
      "count": 0,
      "issues": []
    },
    "codeBlocks": {
      "count": 10,
      "issues": [
        "Code block 6: Horizontal overflow detected",
        "Code block 8: Horizontal overflow detected"
      ]
    },
    "layoutIssues": []
  },
  {
    "page": "/course/engineering-track/ios/03-building-interfaces/04-building-a-form",
    "illustrations": {
      "found": false,
      "count": 0,
      "issues": []
    },
    "codeBlocks": {
      "count": 12,
      "issues": [
        "Code block 6: Horizontal overflow detected"
      ]
    },
    "layoutIssues": []
  },
  {
    "page": "/course/engineering-track/ios/03-building-interfaces/05-custom-components",
    "illustrations": {
      "found": false,
      "count": 0,
      "issues": []
    },
    "codeBlocks": {
      "count": 12,
      "issues": [
        "Code block 4: Horizontal overflow detected"
      ]
    },
    "layoutIssues": []
  },
  {
    "page": "/course/engineering-track/web/01-html-fundamentals/01-what-is-html",
    "illustrations": {
      "found": false,
      "count": 0,
      "issues": []
    },
    "codeBlocks": {
      "count": 10,
      "issues": []
    },
    "layoutIssues": []
  },
  {
    "page": "/course/engineering-track/web/01-html-fundamentals/02-document-structure",
    "illustrations": {
      "found": false,
      "count": 0,
      "issues": []
    },
    "codeBlocks": {
      "count": 38,
      "issues": [
        "Code block 2: Horizontal overflow detected",
        "Code block 8: Horizontal overflow detected",
        "Code block 12: Horizontal overflow detected",
        "Code block 16: Horizontal overflow detected",
        "Code block 22: Horizontal overflow detected",
        "Code block 26: Horizontal overflow detected",
        "Code block 28: Horizontal overflow detected",
        "Code block 38: Horizontal overflow detected"
      ]
    },
    "layoutIssues": []
  },
  {
    "page": "/course/engineering-track/web/01-html-fundamentals/03-semantic-elements",
    "illustrations": {
      "found": false,
      "count": 0,
      "issues": []
    },
    "codeBlocks": {
      "count": 30,
      "issues": []
    },
    "layoutIssues": []
  },
  {
    "page": "/course/engineering-track/web/01-html-fundamentals/04-text-and-links",
    "illustrations": {
      "found": false,
      "count": 0,
      "issues": []
    },
    "codeBlocks": {
      "count": 58,
      "issues": [
        "Code block 6: Horizontal overflow detected",
        "Code block 16: Horizontal overflow detected",
        "Code block 20: Horizontal overflow detected",
        "Code block 24: Horizontal overflow detected",
        "Code block 26: Horizontal overflow detected",
        "Code block 28: Horizontal overflow detected",
        "Code block 34: Horizontal overflow detected",
        "Code block 50: Horizontal overflow detected",
        "Code block 52: Horizontal overflow detected",
        "Code block 58: Horizontal overflow detected"
      ]
    },
    "layoutIssues": []
  },
  {
    "page": "/course/engineering-track/web/01-html-fundamentals/05-forms-and-inputs",
    "illustrations": {
      "found": false,
      "count": 0,
      "issues": []
    },
    "codeBlocks": {
      "count": 84,
      "issues": [
        "Code block 4: Horizontal overflow detected",
        "Code block 18: Horizontal overflow detected",
        "Code block 30: Horizontal overflow detected",
        "Code block 74: Horizontal overflow detected",
        "Code block 80: Horizontal overflow detected",
        "Code block 84: Horizontal overflow detected"
      ]
    },
    "layoutIssues": []
  },
  {
    "page": "/course/engineering-track/web/01-html-fundamentals/06-media-elements",
    "illustrations": {
      "found": false,
      "count": 0,
      "issues": []
    },
    "codeBlocks": {
      "count": 43,
      "issues": [
        "Code block 4: Horizontal overflow detected",
        "Code block 8: Horizontal overflow detected",
        "Code block 18: Horizontal overflow detected",
        "Code block 24: Horizontal overflow detected"
      ]
    },
    "layoutIssues": []
  },
  {
    "page": "/course/engineering-track/web/02-css-mastery/01-how-css-works",
    "illustrations": {
      "found": false,
      "count": 0,
      "issues": []
    },
    "codeBlocks": {
      "count": 38,
      "issues": [
        "Code block 26: Horizontal overflow detected"
      ]
    },
    "layoutIssues": []
  },
  {
    "page": "/course/engineering-track/web/02-css-mastery/02-selectors-deep-dive",
    "illustrations": {
      "found": false,
      "count": 0,
      "issues": []
    },
    "codeBlocks": {
      "count": 64,
      "issues": []
    },
    "layoutIssues": []
  },
  {
    "page": "/course/engineering-track/web/02-css-mastery/03-the-box-model",
    "illustrations": {
      "found": false,
      "count": 0,
      "issues": []
    },
    "codeBlocks": {
      "count": 61,
      "issues": [
        "Code block 5: Horizontal overflow detected",
        "Code block 9: Horizontal overflow detected",
        "Code block 49: Horizontal overflow detected"
      ]
    },
    "layoutIssues": []
  },
  {
    "page": "/course/engineering-track/web/02-css-mastery/04-layout-with-flexbox",
    "illustrations": {
      "found": false,
      "count": 0,
      "issues": []
    },
    "codeBlocks": {
      "count": 46,
      "issues": [
        "Code block 12: Horizontal overflow detected",
        "Code block 24: Horizontal overflow detected"
      ]
    },
    "layoutIssues": []
  },
  {
    "page": "/course/engineering-track/web/02-css-mastery/05-layout-with-grid",
    "illustrations": {
      "found": false,
      "count": 0,
      "issues": []
    },
    "codeBlocks": {
      "count": 50,
      "issues": [
        "Code block 6: Horizontal overflow detected",
        "Code block 10: Horizontal overflow detected",
        "Code block 18: Horizontal overflow detected",
        "Code block 20: Horizontal overflow detected",
        "Code block 44: Horizontal overflow detected"
      ]
    },
    "layoutIssues": []
  },
  {
    "page": "/course/engineering-track/web/02-css-mastery/06-responsive-design",
    "illustrations": {
      "found": false,
      "count": 0,
      "issues": []
    },
    "codeBlocks": {
      "count": 40,
      "issues": [
        "Code block 38: Horizontal overflow detected"
      ]
    },
    "layoutIssues": []
  },
  {
    "page": "/course/engineering-track/web/02-css-mastery/07-custom-properties",
    "illustrations": {
      "found": false,
      "count": 0,
      "issues": []
    },
    "codeBlocks": {
      "count": 46,
      "issues": [
        "Code block 22: Horizontal overflow detected",
        "Code block 32: Horizontal overflow detected",
        "Code block 34: Horizontal overflow detected",
        "Code block 36: Horizontal overflow detected",
        "Code block 38: Horizontal overflow detected"
      ]
    },
    "layoutIssues": []
  },
  {
    "page": "/course/engineering-track/web/02-css-mastery/08-transitions-and-animations",
    "illustrations": {
      "found": false,
      "count": 0,
      "issues": []
    },
    "codeBlocks": {
      "count": 50,
      "issues": [
        "Code block 12: Horizontal overflow detected",
        "Code block 22: Horizontal overflow detected",
        "Code block 24: Horizontal overflow detected",
        "Code block 26: Horizontal overflow detected",
        "Code block 50: Horizontal overflow detected"
      ]
    },
    "layoutIssues": []
  },
  {
    "page": "/course/engineering-track/web/03-javascript-essentials/01-what-is-javascript",
    "illustrations": {
      "found": false,
      "count": 0,
      "issues": []
    },
    "codeBlocks": {
      "count": 18,
      "issues": []
    },
    "layoutIssues": []
  },
  {
    "page": "/course/engineering-track/web/03-javascript-essentials/02-variables-and-types",
    "illustrations": {
      "found": false,
      "count": 0,
      "issues": []
    },
    "codeBlocks": {
      "count": 42,
      "issues": [
        "Code block 8: Horizontal overflow detected"
      ]
    },
    "layoutIssues": []
  },
  {
    "page": "/course/engineering-track/web/03-javascript-essentials/03-functions",
    "illustrations": {
      "found": false,
      "count": 0,
      "issues": []
    },
    "codeBlocks": {
      "count": 36,
      "issues": [
        "Code block 12: Horizontal overflow detected"
      ]
    },
    "layoutIssues": []
  },
  {
    "page": "/course/engineering-track/web/03-javascript-essentials/04-control-flow",
    "illustrations": {
      "found": false,
      "count": 0,
      "issues": []
    },
    "codeBlocks": {
      "count": 42,
      "issues": [
        "Code block 12: Horizontal overflow detected",
        "Code block 16: Horizontal overflow detected"
      ]
    },
    "layoutIssues": []
  },
  {
    "page": "/course/engineering-track/web/03-javascript-essentials/05-dom-manipulation",
    "illustrations": {
      "found": false,
      "count": 0,
      "issues": []
    },
    "codeBlocks": {
      "count": 49,
      "issues": [
        "Code block 13: Horizontal overflow detected",
        "Code block 39: Horizontal overflow detected"
      ]
    },
    "layoutIssues": []
  },
  {
    "page": "/course/engineering-track/web/03-javascript-essentials/06-events",
    "illustrations": {
      "found": false,
      "count": 0,
      "issues": []
    },
    "codeBlocks": {
      "count": 46,
      "issues": [
        "Code block 12: Horizontal overflow detected",
        "Code block 14: Horizontal overflow detected",
        "Code block 16: Horizontal overflow detected",
        "Code block 18: Horizontal overflow detected",
        "Code block 24: Horizontal overflow detected",
        "Code block 30: Horizontal overflow detected",
        "Code block 34: Horizontal overflow detected",
        "Code block 36: Horizontal overflow detected",
        "Code block 42: Horizontal overflow detected"
      ]
    },
    "layoutIssues": []
  },
  {
    "page": "/course/engineering-track/web/03-javascript-essentials/07-working-with-data",
    "illustrations": {
      "found": false,
      "count": 0,
      "issues": []
    },
    "codeBlocks": {
      "count": 43,
      "issues": [
        "Code block 20: Horizontal overflow detected",
        "Code block 24: Horizontal overflow detected",
        "Code block 42: Horizontal overflow detected",
        "Code block 43: Height too small (24px)"
      ]
    },
    "layoutIssues": []
  },
  {
    "page": "/course/engineering-track/web/03-javascript-essentials/08-modern-javascript",
    "illustrations": {
      "found": false,
      "count": 0,
      "issues": []
    },
    "codeBlocks": {
      "count": 48,
      "issues": [
        "Code block 4: Horizontal overflow detected",
        "Code block 40: Horizontal overflow detected"
      ]
    },
    "layoutIssues": []
  },
  {
    "page": "/course/engineering-track/web/04-building-components/01-component-thinking",
    "illustrations": {
      "found": false,
      "count": 0,
      "issues": []
    },
    "codeBlocks": {
      "count": 1,
      "issues": []
    },
    "layoutIssues": []
  },
  {
    "page": "/course/engineering-track/web/04-building-components/02-building-a-button",
    "illustrations": {
      "found": false,
      "count": 0,
      "issues": []
    },
    "codeBlocks": {
      "count": 16,
      "issues": [
        "Code block 14: Horizontal overflow detected",
        "Code block 16: Horizontal overflow detected"
      ]
    },
    "layoutIssues": []
  },
  {
    "page": "/course/engineering-track/web/04-building-components/03-building-a-card",
    "illustrations": {
      "found": false,
      "count": 0,
      "issues": []
    },
    "codeBlocks": {
      "count": 18,
      "issues": [
        "Code block 2: Horizontal overflow detected"
      ]
    },
    "layoutIssues": []
  },
  {
    "page": "/course/engineering-track/web/04-building-components/04-building-a-modal",
    "illustrations": {
      "found": false,
      "count": 0,
      "issues": []
    },
    "codeBlocks": {
      "count": 8,
      "issues": [
        "Code block 2: Horizontal overflow detected",
        "Code block 8: Horizontal overflow detected"
      ]
    },
    "layoutIssues": []
  },
  {
    "page": "/course/engineering-track/web/04-building-components/05-building-a-form",
    "illustrations": {
      "found": false,
      "count": 0,
      "issues": []
    },
    "codeBlocks": {
      "count": 6,
      "issues": [
        "Code block 2: Horizontal overflow detected",
        "Code block 6: Horizontal overflow detected"
      ]
    },
    "layoutIssues": []
  },
  {
    "page": "/course/engineering-track/web/04-building-components/06-patterns-and-composition",
    "illustrations": {
      "found": false,
      "count": 0,
      "issues": []
    },
    "codeBlocks": {
      "count": 16,
      "issues": [
        "Code block 6: Horizontal overflow detected",
        "Code block 10: Horizontal overflow detected",
        "Code block 12: Horizontal overflow detected"
      ]
    },
    "layoutIssues": []
  },
  {
    "page": "/course/engineering-track/web/05-design-systems-in-code/01-tokens-in-code",
    "illustrations": {
      "found": false,
      "count": 0,
      "issues": []
    },
    "codeBlocks": {
      "count": 8,
      "issues": []
    },
    "layoutIssues": []
  },
  {
    "page": "/course/engineering-track/web/05-design-systems-in-code/02-building-a-token-system",
    "illustrations": {
      "found": false,
      "count": 0,
      "issues": []
    },
    "codeBlocks": {
      "count": 12,
      "issues": []
    },
    "layoutIssues": []
  },
  {
    "page": "/course/engineering-track/web/05-design-systems-in-code/03-component-api-design",
    "illustrations": {
      "found": false,
      "count": 0,
      "issues": []
    },
    "codeBlocks": {
      "count": 16,
      "issues": []
    },
    "layoutIssues": []
  },
  {
    "page": "/course/engineering-track/web/05-design-systems-in-code/04-documentation-for-devs",
    "illustrations": {
      "found": false,
      "count": 0,
      "issues": []
    },
    "codeBlocks": {
      "count": 10,
      "issues": [
        "Code block 5: Height too small (28px)",
        "Code block 10: Height too small (28px)"
      ]
    },
    "layoutIssues": []
  },
  {
    "page": "/course/engineering-track/web/05-design-systems-in-code/05-versioning-and-releases",
    "illustrations": {
      "found": false,
      "count": 0,
      "issues": []
    },
    "codeBlocks": {
      "count": 8,
      "issues": [
        "Code block 3: Height too small (28px)",
        "Code block 5: Horizontal overflow detected",
        "Code block 8: Height too small (28px)"
      ]
    },
    "layoutIssues": []
  }
]